{"assets/images/a53_1.png":["assets/images/a53_1.png"],"assets/images/a53_2.png":["assets/images/a53_2.png"],"assets/images/a53_3.png":["assets/images/a53_3.png"],"assets/images/apple_watch_series_7_1.png":["assets/images/apple_watch_series_7_1.png"],"assets/images/apple_watch_series_7_2.png":["assets/images/apple_watch_series_7_2.png"],"assets/images/apple_watch_series_7_3.png":["assets/images/apple_watch_series_7_3.png"],"assets/images/beats_studio_3-1.png":["assets/images/beats_studio_3-1.png"],"assets/images/beats_studio_3-2.png":["assets/images/beats_studio_3-2.png"],"assets/images/beats_studio_3-3.png":["assets/images/beats_studio_3-3.png"],"assets/images/beats_studio_3-4.png":["assets/images/beats_studio_3-4.png"],"assets/images/empty_cart.png":["assets/images/empty_cart.png"],"assets/images/galaxy_watch_4_1.png":["assets/images/galaxy_watch_4_1.png"],"assets/images/galaxy_watch_4_2.png":["assets/images/galaxy_watch_4_2.png"],"assets/images/galaxy_watch_4_3.png":["assets/images/galaxy_watch_4_3.png"],"assets/images/github.png":["assets/images/github.png"],"assets/images/logo.png":["assets/images/logo.png"],"assets/images/profile_pic.png":["assets/images/profile_pic.png"],"assets/images/samsung_q_60_a_1.png":["assets/images/samsung_q_60_a_1.png"],"assets/images/samsung_q_60_a_2.png":["assets/images/samsung_q_60_a_2.png"],"assets/images/shopping.png":["assets/images/shopping.png"],"assets/images/sony_x_80_j_1.png":["assets/images/sony_x_80_j_1.png"],"assets/images/sony_x_80_j_2.png":["assets/images/sony_x_80_j_2.png"],"assets/images/tab_s7_fe_1.png":["assets/images/tab_s7_fe_1.png"],"assets/images/tab_s7_fe_2.png":["assets/images/tab_s7_fe_2.png"],"assets/images/tab_s7_fe_3.png":["assets/images/tab_s7_fe_3.png"],"assets/images/tab_s8_1.png":["assets/images/tab_s8_1.png"],"assets/images/tab_s8_2.png":["assets/images/tab_s8_2.png"],"assets/images/tab_s8_3.png":["assets/images/tab_s8_3.png"],"packages/font_awesome_flutter/lib/fonts/fa-brands-400.ttf":["packages/font_awesome_flutter/lib/fonts/fa-brands-400.ttf"],"packages/font_awesome_flutter/lib/fonts/fa-regular-400.ttf":["packages/font_awesome_flutter/lib/fonts/fa-regular-400.ttf"],"packages/font_awesome_flutter/lib/fonts/fa-solid-900.ttf":["packages/font_awesome_flutter/lib/fonts/fa-solid-900.ttf"]}